LabelFusion/__init__.py
LabelFusion/fusion_wrappers.py
LabelFusion/fusionator.py
LabelFusion/itkUtils.py
LabelFusion/majority_voting.py
LabelFusion/simple.py
LabelFusion/utils.py
LabelFusion/wrapper.py
labelfusion-1.0.15.data/scripts/fusion_run
labelfusion-1.0.15.dist-info/licenses/LICENSE
labelfusion-1.0.15.dist-info/METADATA
labelfusion-1.0.15.dist-info/WHEEL
labelfusion-1.0.15.dist-info/top_level.txt
labelfusion-1.0.15.dist-info/RECORD
