Metadata-Version: 2.4
Name: LabelFusion
Version: 1.0.15
Summary: Label fusion strategies for multi-class labels.
Home-page: https://github.com/FETS-AI/LabelFusion
Author: Megh Bhalerao, Sarthak Pati
Author-email: admin@fets.ai
License: Apache-2.0
Keywords: semantic,segmentation,label-fusion,fusion
Classifier: Development Status :: 5 - Production/Stable
Classifier: Intended Audience :: Science/Research
Classifier: License :: OSI Approved :: Apache Software License
Classifier: Natural Language :: English
Classifier: Operating System :: OS Independent
Classifier: Programming Language :: Python :: 3.9
Classifier: Programming Language :: Python :: 3.10
Classifier: Programming Language :: Python :: 3.11
Classifier: Programming Language :: Python :: 3.12
Requires-Python: >=3.9
License-File: LICENSE
Requires-Dist: numpy>=1.19.2
Requires-Dist: SimpleITK!=2.0.*
Requires-Dist: SimpleITK!=2.2.1
Requires-Dist: setuptools
Requires-Dist: wheel
Requires-Dist: twine
Requires-Dist: keyring
Requires-Dist: black
Requires-Dist: psutil
Requires-Dist: requests
Dynamic: author
Dynamic: author-email
Dynamic: classifier
Dynamic: description
Dynamic: description-content-type
Dynamic: home-page
Dynamic: keywords
Dynamic: license
Dynamic: license-file
Dynamic: requires-dist
Dynamic: requires-python
Dynamic: summary
